[
    {
        "type": "git_post",
        "login": "Git Foundation",
        "x": 0,
        "y": 0,
        "username": "Git Foundation",
        "color": "#f05032",
        "has_terrace": true,
        "roofStyle": 1,
        "doorStyle": 3,
        "wallStyle": 0,
        "facing": "down"
    },
    {
        "type": "git_post",
        "login": "Commit Node 354",
        "x": 3.0,
        "y": -3.0,
        "username": "Commit Node 354",
        "color": "#f05032",
        "roofStyle": 1,
        "doorStyle": 3,
        "windowStyle": 3,
        "chimneyStyle": 2,
        "wallStyle": 0,
        "has_terrace": true,
        "facing": "left"
    },
    {
        "type": "git_post",
        "login": "Commit Node 697",
        "x": 5.0,
        "y": -3.0,
        "username": "Commit Node 697",
        "color": "#f05032",
        "roofStyle": 1,
        "doorStyle": 3,
        "windowStyle": 2,
        "chimneyStyle": 2,
        "wallStyle": 0,
        "has_terrace": true,
        "facing": "left"
    },
    {
        "type": "activity_house",
        "login": "Algorithm Base",
        "x": 7.0,
        "y": -3.0,
        "username": "Algorithm Base",
        "color": "#2c9c26",
        "roofStyle": 2,
        "doorStyle": 0,
        "windowStyle": 1,
        "chimneyStyle": 0,
        "wallStyle": 2,
        "has_terrace": true,
        "facing": "left"
    },
    {
        "type": "tree",
        "x": 9.0,
        "y": -3.0,
        "obstacle": "tree",
        "facing": "left"
    },
    {
        "type": "activity_house",
        "login": "Algorithm Hub",
        "x": 3.0,
        "y": -5.0,
        "username": "Algorithm Hub",
        "color": "#7f8cc5",
        "roofStyle": 3,
        "doorStyle": 3,
        "windowStyle": 0,
        "chimneyStyle": 0,
        "wallStyle": 0,
        "has_terrace": false,
        "facing": "left",
        "is_upgrade_target": true
    },
    {
        "type": "tree",
        "x": 5.0,
        "y": -5.0,
        "obstacle": "tree",
        "facing": "left"
    },
    {
        "type": "activity_house",
        "login": "Coder's Den",
        "x": 7.0,
        "y": -5.0,
        "username": "Coder's Den",
        "color": "#7046f9",
        "roofStyle": 3,
        "doorStyle": 0,
        "windowStyle": 0,
        "chimneyStyle": 2,
        "wallStyle": 3,
        "has_terrace": false,
        "facing": "left"
    },
    {
        "type": "activity_house",
        "login": "Data Den",
        "x": 9.0,
        "y": -5.0,
        "username": "Data Den",
        "color": "#36dffb",
        "roofStyle": 3,
        "doorStyle": 2,
        "windowStyle": 1,
        "chimneyStyle": 3,
        "wallStyle": 3,
        "has_terrace": false,
        "facing": "left"
    },
    {
        "type": "tree",
        "x": 3.0,
        "y": -7.0,
        "obstacle": "tree",
        "facing": "left"
    },
    {
        "type": "activity_house",
        "login": "Cloud Den",
        "x": 5.0,
        "y": -7.0,
        "has_terrace": true,
        "username": "Cloud Den",
        "color": "#9eb8bb",
        "roofStyle": 1,
        "doorStyle": 2,
        "windowStyle": 3,
        "chimneyStyle": 0,
        "wallStyle": 3,
        "facing": "left"
    },
    {
        "type": "tree",
        "x": 7.0,
        "y": -7.0,
        "obstacle": "tree",
        "facing": "left"
    },
    {
        "type": "tree",
        "x": 9.0,
        "y": -7.0,
        "obstacle": "tree",
        "facing": "left"
    },
    {
        "type": "activity_house",
        "login": "Binary Villa",
        "x": 3.0,
        "y": -9.0,
        "username": "Binary Villa",
        "color": "#4128f5",
        "roofStyle": 0,
        "doorStyle": 1,
        "windowStyle": 2,
        "chimneyStyle": 0,
        "wallStyle": 3,
        "has_terrace": true,
        "facing": "left"
    },
    {
        "type": "tree",
        "x": 5.0,
        "y": -9.0,
        "obstacle": "tree",
        "facing": "left"
    },
    {
        "type": "activity_house",
        "login": "Syntax Loft",
        "x": 7.0,
        "y": -9.0,
        "username": "Syntax Loft",
        "color": "#e69dd1",
        "roofStyle": 2,
        "doorStyle": 2,
        "windowStyle": 1,
        "chimneyStyle": 1,
        "wallStyle": 1,
        "has_terrace": false,
        "facing": "left"
    },
    {
        "type": "tree",
        "x": 9.0,
        "y": -9.0,
        "obstacle": "tree",
        "facing": "left"
    },
    {
        "type": "tree",
        "x": -3.0,
        "y": -3.0,
        "obstacle": "tree",
        "facing": "right"
    },
    {
        "type": "activity_house",
        "login": "Python Palace",
        "x": -5.0,
        "y": -3.0,
        "username": "Python Palace",
        "color": "#ea0235",
        "roofStyle": 2,
        "doorStyle": 2,
        "windowStyle": 0,
        "chimneyStyle": 2,
        "wallStyle": 3,
        "has_terrace": false,
        "facing": "right"
    },
    {
        "type": "activity_house",
        "login": "Server Garrison",
        "x": -7.0,
        "y": -3.0,
        "username": "Server Garrison",
        "color": "#c0538b",
        "roofStyle": 0,
        "doorStyle": 0,
        "windowStyle": 1,
        "chimneyStyle": 3,
        "wallStyle": 0,
        "has_terrace": false,
        "facing": "right"
    }
]